[{"year": 2025, "state": 10, "subject": 2, "rank": "1", "registration_number": "511000454", "raw_score": "80", "calculated_score": "699", "percentile": "97.67", "grade": "B"}, {"year": 2025, "state": 10, "subject": 2, "rank": "2", "registration_number": "511000291", "raw_score": "79", "calculated_score": "694", "percentile": "97.39", "grade": "B"}, {"year": 2025, "state": 10, "subject": 2, "rank": "3", "registration_number": "511000451", "raw_score": "76", "calculated_score": "679", "percentile": "96.3", "grade": "B"}, {"year": 2025, "state": 10, "subject": 2, "rank": "4 = 5", "registration_number": "511000303", "raw_score": "74", "calculated_score": "671", "percentile": "95.64", "grade": "B"}, {"year": 2025, "state": 10, "subject": 2, "rank": "4 = 5", "registration_number": "511000294", "raw_score": "74", "calculated_score": "671", "percentile": "95.64", "grade": "B"}, {"year": 2025, "state": 10, "subject": 2, "rank": "6 = 7", "registration_number": "511000276", "raw_score": "73", "calculated_score": "667", "percentile": "95.27", "grade": "B"}, {"year": 2025, "state": 10, "subject": 2, "rank": "6 = 7", "registration_number": "511000307", "raw_score": "73", "calculated_score": "667", "percentile": "95.27", "grade": "B"}, {"year": 2025, "state": 10, "subject": 2, "rank": "8 = 9", "registration_number": "511000457", "raw_score": "71", "calculated_score": "659", "percentile": "94.36", "grade": "B"}, {"year": 2025, "state": 10, "subject": 2, "rank": "8 = 9", "registration_number": "511000461", "raw_score": "71", "calculated_score": "659", "percentile": "94.36", "grade": "B"}, {"year": 2025, "state": 10, "subject": 2, "rank": "10", "registration_number": "511000489", "raw_score": "70", "calculated_score": "654", "percentile": "93.81", "grade": "B"}, {"year": 2025, "state": 10, "subject": 2, "rank": "11 = 12", "registration_number": "511000406", "raw_score": "66", "calculated_score": "639", "percentile": "91.82", "grade": "B-"}, {"year": 2025, "state": 10, "subject": 2, "rank": "11 = 12", "registration_number": "511000122", "raw_score": "66", "calculated_score": "639", "percentile": "91.82", "grade": "B-"}, {"year": 2025, "state": 10, "subject": 2, "rank": "13 = 15", "registration_number": "511000284", "raw_score": "63", "calculated_score": "628", "percentile": "90.03", "grade": "B-"}, {"year": 2025, "state": 10, "subject": 2, "rank": "13 = 15", "registration_number": "511000448", "raw_score": "63", "calculated_score": "628", "percentile": "90.03", "grade": "B-"}, {"year": 2025, "state": 10, "subject": 2, "rank": "13 = 15", "registration_number": "511000641", "raw_score": "63", "calculated_score": "628", "percentile": "90.03", "grade": "B-"}, {"year": 2025, "state": 10, "subject": 2, "rank": "16 = 18", "registration_number": "511000450", "raw_score": "62", "calculated_score": "624", "percentile": "89.34", "grade": "B-"}, {"year": 2025, "state": 10, "subject": 2, "rank": "16 = 18", "registration_number": "511000280", "raw_score": "62", "calculated_score": "624", "percentile": "89.34", "grade": "B-"}, {"year": 2025, "state": 10, "subject": 2, "rank": "16 = 18", "registration_number": "511000249", "raw_score": "62", "calculated_score": "624", "percentile": "89.34", "grade": "B-"}, {"year": 2025, "state": 10, "subject": 2, "rank": "19", "registration_number": "511000623", "raw_score": "61", "calculated_score": "621", "percentile": "88.68", "grade": "B-"}, {"year": 2025, "state": 10, "subject": 2, "rank": "20 = 21", "registration_number": "511000273", "raw_score": "60", "calculated_score": "617", "percentile": "87.98", "grade": "B-"}, {"year": 2025, "state": 10, "subject": 2, "rank": "20 = 21", "registration_number": "511000305", "raw_score": "60", "calculated_score": "617", "percentile": "87.98", "grade": "B-"}, {"year": 2025, "state": 10, "subject": 2, "rank": "22", "registration_number": "511000392", "raw_score": "59", "calculated_score": "613", "percentile": "87.26", "grade": "B-"}, {"year": 2025, "state": 10, "subject": 2, "rank": "23", "registration_number": "511000464", "raw_score": "58", "calculated_score": "610", "percentile": "86.51", "grade": "B-"}, {"year": 2025, "state": 10, "subject": 2, "rank": "24", "registration_number": "511000460", "raw_score": "56", "calculated_score": "604", "percentile": "85.09", "grade": "B-"}, {"year": 2025, "state": 10, "subject": 2, "rank": "25 = 28", "registration_number": "511000563", "raw_score": "55", "calculated_score": "601", "percentile": "84.36", "grade": "B-"}, {"year": 2025, "state": 10, "subject": 2, "rank": "25 = 28", "registration_number": "511000279", "raw_score": "55", "calculated_score": "601", "percentile": "84.36", "grade": "B-"}, {"year": 2025, "state": 10, "subject": 2, "rank": "25 = 28", "registration_number": "511000198", "raw_score": "55", "calculated_score": "601", "percentile": "84.36", "grade": "B-"}, {"year": 2025, "state": 10, "subject": 2, "rank": "25 = 28", "registration_number": "511000021", "raw_score": "55", "calculated_score": "601", "percentile": "84.36", "grade": "B-"}, {"year": 2025, "state": 10, "subject": 2, "rank": "29", "registration_number": "511000293", "raw_score": "54", "calculated_score": "598", "percentile": "83.59", "grade": "C"}, {"year": 2025, "state": 10, "subject": 2, "rank": "30 = 31", "registration_number": "511000251", "raw_score": "53", "calculated_score": "594", "percentile": "82.69", "grade": "C"}, {"year": 2025, "state": 10, "subject": 2, "rank": "30 = 31", "registration_number": "511000443", "raw_score": "53", "calculated_score": "594", "percentile": "82.69", "grade": "C"}, {"year": 2025, "state": 10, "subject": 2, "rank": "32", "registration_number": "511000614", "raw_score": "52", "calculated_score": "590", "percentile": "81.68", "grade": "C"}, {"year": 2025, "state": 10, "subject": 2, "rank": "33 = 34", "registration_number": "511000554", "raw_score": "50", "calculated_score": "583", "percentile": "79.56", "grade": "C"}, {"year": 2025, "state": 10, "subject": 2, "rank": "33 = 34", "registration_number": "511000167", "raw_score": "50", "calculated_score": "583", "percentile": "79.56", "grade": "C"}, {"year": 2025, "state": 10, "subject": 2, "rank": "35", "registration_number": "511000064", "raw_score": "49", "calculated_score": "579", "percentile": "78.45", "grade": "C"}, {"year": 2025, "state": 10, "subject": 2, "rank": "36 = 37", "registration_number": "511000238", "raw_score": "48", "calculated_score": "575", "percentile": "77.33", "grade": "C"}, {"year": 2025, "state": 10, "subject": 2, "rank": "36 = 37", "registration_number": "511000296", "raw_score": "48", "calculated_score": "575", "percentile": "77.33", "grade": "C"}, {"year": 2025, "state": 10, "subject": 2, "rank": "38", "registration_number": "511000009", "raw_score": "45", "calculated_score": "563", "percentile": "73.67", "grade": "C"}, {"year": 2025, "state": 10, "subject": 2, "rank": "39 = 40", "registration_number": "511000056", "raw_score": "44", "calculated_score": "557", "percentile": "72.04", "grade": "C"}, {"year": 2025, "state": 10, "subject": 2, "rank": "39 = 40", "registration_number": "511000499", "raw_score": "44", "calculated_score": "557", "percentile": "72.04", "grade": "C"}, {"year": 2025, "state": 10, "subject": 2, "rank": "41", "registration_number": "511000278", "raw_score": "43", "calculated_score": "554", "percentile": "70.45", "grade": "C"}, {"year": 2025, "state": 10, "subject": 2, "rank": "42 = 44", "registration_number": "511000162", "raw_score": "42", "calculated_score": "549", "percentile": "68.82", "grade": "C-"}, {"year": 2025, "state": 10, "subject": 2, "rank": "42 = 44", "registration_number": "511000543", "raw_score": "42", "calculated_score": "549", "percentile": "68.82", "grade": "C-"}, {"year": 2025, "state": 10, "subject": 2, "rank": "42 = 44", "registration_number": "511000355", "raw_score": "42", "calculated_score": "549", "percentile": "68.82", "grade": "C-"}, {"year": 2025, "state": 10, "subject": 2, "rank": "45 = 46", "registration_number": "511000422", "raw_score": "41", "calculated_score": "544", "percentile": "66.99", "grade": "C-"}, {"year": 2025, "state": 10, "subject": 2, "rank": "45 = 46", "registration_number": "511000666", "raw_score": "41", "calculated_score": "544", "percentile": "66.99", "grade": "C-"}, {"year": 2025, "state": 10, "subject": 2, "rank": "47", "registration_number": "511000286", "raw_score": "40", "calculated_score": "539", "percentile": "65", "grade": "C-"}, {"year": 2025, "state": 10, "subject": 2, "rank": "48 = 49", "registration_number": "511000201", "raw_score": "39", "calculated_score": "533", "percentile": "63.02", "grade": "C-"}, {"year": 2025, "state": 10, "subject": 2, "rank": "48 = 49", "registration_number": "511000071", "raw_score": "39", "calculated_score": "533", "percentile": "63.02", "grade": "C-"}, {"year": 2025, "state": 10, "subject": 2, "rank": "50", "registration_number": "511000045", "raw_score": "38", "calculated_score": "527", "percentile": "60.83", "grade": "C-"}, {"year": 2025, "state": 10, "subject": 2, "rank": "51 = 53", "registration_number": "511000223", "raw_score": "37", "calculated_score": "521", "percentile": "58.41", "grade": "C-"}, {"year": 2025, "state": 10, "subject": 2, "rank": "51 = 53", "registration_number": "511000283", "raw_score": "37", "calculated_score": "521", "percentile": "58.41", "grade": "C-"}, {"year": 2025, "state": 10, "subject": 2, "rank": "51 = 53", "registration_number": "511000589", "raw_score": "37", "calculated_score": "521", "percentile": "58.41", "grade": "C-"}, {"year": 2025, "state": 10, "subject": 2, "rank": "54", "registration_number": "511000183", "raw_score": "36", "calculated_score": "515", "percentile": "56.04", "grade": "C-"}, {"year": 2025, "state": 10, "subject": 2, "rank": "55 = 59", "registration_number": "511000185", "raw_score": "35", "calculated_score": "509", "percentile": "53.4", "grade": "C-"}, {"year": 2025, "state": 10, "subject": 2, "rank": "55 = 59", "registration_number": "511000261", "raw_score": "35", "calculated_score": "509", "percentile": "53.4", "grade": "C-"}, {"year": 2025, "state": 10, "subject": 2, "rank": "55 = 59", "registration_number": "511000344", "raw_score": "35", "calculated_score": "509", "percentile": "53.4", "grade": "C-"}, {"year": 2025, "state": 10, "subject": 2, "rank": "55 = 59", "registration_number": "511000609", "raw_score": "35", "calculated_score": "509", "percentile": "53.4", "grade": "C-"}, {"year": 2025, "state": 10, "subject": 2, "rank": "55 = 59", "registration_number": "511000631", "raw_score": "35", "calculated_score": "509", "percentile": "53.4", "grade": "C-"}, {"year": 2025, "state": 10, "subject": 2, "rank": "60", "registration_number": "511000200", "raw_score": "34", "calculated_score": "501", "percentile": "50.58", "grade": "C-"}, {"year": 2025, "state": 10, "subject": 2, "rank": "61 = 62", "registration_number": "511000586", "raw_score": "33", "calculated_score": "494", "percentile": "47.57", "grade": "D"}, {"year": 2025, "state": 10, "subject": 2, "rank": "61 = 62", "registration_number": "511000539", "raw_score": "33", "calculated_score": "494", "percentile": "47.57", "grade": "D"}, {"year": 2025, "state": 10, "subject": 2, "rank": "63", "registration_number": "511000166", "raw_score": "32", "calculated_score": "485", "percentile": "44.07", "grade": "D"}, {"year": 2025, "state": 10, "subject": 2, "rank": "64", "registration_number": "511000463", "raw_score": "31", "calculated_score": "476", "percentile": "40.59", "grade": "D"}, {"year": 2025, "state": 10, "subject": 2, "rank": "65", "registration_number": "511000062", "raw_score": "30", "calculated_score": "467", "percentile": "37.14", "grade": "D"}, {"year": 2025, "state": 10, "subject": 2, "rank": "66", "registration_number": "511000252", "raw_score": "29", "calculated_score": "457", "percentile": "33.48", "grade": "D"}, {"year": 2025, "state": 10, "subject": 2, "rank": "67 = 70", "registration_number": "511000519", "raw_score": "28", "calculated_score": "447", "percentile": "29.91", "grade": "D-"}, {"year": 2025, "state": 10, "subject": 2, "rank": "67 = 70", "registration_number": "511000564", "raw_score": "28", "calculated_score": "447", "percentile": "29.91", "grade": "D-"}, {"year": 2025, "state": 10, "subject": 2, "rank": "67 = 70", "registration_number": "511000413", "raw_score": "28", "calculated_score": "447", "percentile": "29.91", "grade": "D-"}, {"year": 2025, "state": 10, "subject": 2, "rank": "67 = 70", "registration_number": "511000664", "raw_score": "28", "calculated_score": "447", "percentile": "29.91", "grade": "D-"}, {"year": 2025, "state": 10, "subject": 2, "rank": "71", "registration_number": "511000562", "raw_score": "27", "calculated_score": "436", "percentile": "26.21", "grade": "D-"}, {"year": 2025, "state": 10, "subject": 2, "rank": "72 = 73", "registration_number": "511000546", "raw_score": "26", "calculated_score": "424", "percentile": "22.38", "grade": "D-"}, {"year": 2025, "state": 10, "subject": 2, "rank": "72 = 73", "registration_number": "511000271", "raw_score": "26", "calculated_score": "424", "percentile": "22.38", "grade": "D-"}, {"year": 2025, "state": 10, "subject": 2, "rank": "74 = 76", "registration_number": "511000425", "raw_score": "25", "calculated_score": "412", "percentile": "18.99", "grade": "D-"}, {"year": 2025, "state": 10, "subject": 2, "rank": "74 = 76", "registration_number": "511000444", "raw_score": "25", "calculated_score": "412", "percentile": "18.99", "grade": "D-"}, {"year": 2025, "state": 10, "subject": 2, "rank": "74 = 76", "registration_number": "511000684", "raw_score": "25", "calculated_score": "412", "percentile": "18.99", "grade": "D-"}, {"year": 2025, "state": 10, "subject": 2, "rank": "77", "registration_number": "511000019", "raw_score": "24", "calculated_score": "400", "percentile": "15.9", "grade": "D-"}, {"year": 2025, "state": 10, "subject": 2, "rank": "78", "registration_number": "511000560", "raw_score": "23", "calculated_score": "388", "percentile": "12.96", "grade": "F"}]